schemaless.py
setup.py
sqlite_schemaless.egg-info/PKG-INFO
sqlite_schemaless.egg-info/SOURCES.txt
sqlite_schemaless.egg-info/dependency_links.txt
sqlite_schemaless.egg-info/requires.txt
sqlite_schemaless.egg-info/top_level.txt