Metadata-Version: 1.1
Name: sqlite-schemaless
Version: 0.1.2
Summary: schemaless database on top of sqlite
Home-page: http://github.com/coleifer/sqlite-schemaless/
Author: Charles Leifer
Author-email: coleifer@gmail.com
License: UNKNOWN
Platform: UNKNOWN
Classifier: Development Status :: 5 - Production/Stable
Classifier: Intended Audience :: Developers
Classifier: License :: OSI Approved :: MIT License
Classifier: Operating System :: OS Independent
Classifier: Programming Language :: Python
